odoo/addons/delivery_state/README.rst
odoo/addons/delivery_state/__init__.py
odoo/addons/delivery_state/__manifest__.py
odoo/addons/delivery_state/data/ir_cron_data.xml
odoo/addons/delivery_state/data/mail_template.xml
odoo/addons/delivery_state/i18n/delivery_state.pot
odoo/addons/delivery_state/i18n/es.po
odoo/addons/delivery_state/i18n/nl.po
odoo/addons/delivery_state/models/__init__.py
odoo/addons/delivery_state/models/delivery_carrier.py
odoo/addons/delivery_state/models/res_company.py
odoo/addons/delivery_state/models/res_config_settings.py
odoo/addons/delivery_state/models/stock_picking.py
odoo/addons/delivery_state/readme/CONFIGURE.rst
odoo/addons/delivery_state/readme/CONTRIBUTORS.rst
odoo/addons/delivery_state/readme/DESCRIPTION.rst
odoo/addons/delivery_state/readme/USAGE.rst
odoo/addons/delivery_state/static/description/icon.png
odoo/addons/delivery_state/static/description/index.html
odoo/addons/delivery_state/tests/__init__.py
odoo/addons/delivery_state/tests/test_delivery_state.py
odoo/addons/delivery_state/views/res_config_settings_views.xml
odoo/addons/delivery_state/views/stock_picking_views.xml
odoo12_addon_delivery_state-12.0.2.0.1.dist-info/METADATA
odoo12_addon_delivery_state-12.0.2.0.1.dist-info/WHEEL
odoo12_addon_delivery_state-12.0.2.0.1.dist-info/top_level.txt
odoo12_addon_delivery_state-12.0.2.0.1.dist-info/RECORD
